delta_table/__init__.py
delta_table/delta_table_utils.py
delta_table/utils/__init__.py
delta_table/utils/logger.py
delta_table_utils-0.0.17.dist-info/LICENSE
delta_table_utils-0.0.17.dist-info/METADATA
delta_table_utils-0.0.17.dist-info/WHEEL
delta_table_utils-0.0.17.dist-info/top_level.txt
delta_table_utils-0.0.17.dist-info/RECORD
