Metadata-Version: 2.1
Name: delta-table-utils
Version: 0.0.17
Summary: Delta table utilities.
Author-email: Mathemagical <sarah.dorich.biz@gmail.com>
Classifier: Programming Language :: Python :: 3
Classifier: License :: OSI Approved :: MIT License
Classifier: Operating System :: OS Independent
Requires-Python: >=3.8
License-File: LICENSE
